LICENSE
MANIFEST.in
README.rst
setup.py
django_fiobank/__init__.py
django_fiobank/admin.py
django_fiobank/emails.py
django_fiobank/graph.py
django_fiobank/models.py
django_fiobank/utils.py
django_fiobank.egg-info/PKG-INFO
django_fiobank.egg-info/SOURCES.txt
django_fiobank.egg-info/dependency_links.txt
django_fiobank.egg-info/requires.txt
django_fiobank.egg-info/top_level.txt
django_fiobank/locale/cs/LC_MESSAGES/django.mo
django_fiobank/locale/cs/LC_MESSAGES/django.po
django_fiobank/locale/en/LC_MESSAGES/django.mo
django_fiobank/locale/en/LC_MESSAGES/django.po
django_fiobank/management/__init__.py
django_fiobank/management/commands/__init__.py
django_fiobank/management/commands/fiochecktokentimevalidity.py
django_fiobank/management/commands/fiodownload.py
django_fiobank/migrations/0001_initial.py
django_fiobank/migrations/0002_auto_20150523_1926.py
django_fiobank/migrations/__init__.py
django_fiobank/templates/django_fiobank/admin/account/change.html
django_fiobank/templates/django_fiobank/emails/base.html
django_fiobank/templates/django_fiobank/emails/base.txt
django_fiobank/templates/django_fiobank/emails/token_expired.html
django_fiobank/templates/django_fiobank/emails/token_expired.txt
django_fiobank/templatetags/__init__.py
django_fiobank/templatetags/fiobank_tags.py
django_fiobank/tests/__init__.py
django_fiobank/tests/emails_test.py
django_fiobank/tests/models_test.py
django_fiobank/tests/utils_test.py