Metadata-Version: 1.1
Name: django-fiobank
Version: 0.1.1
Summary: Django-app for managing and processing Fio Bank transaction
Home-page: https://github.com/rbas/django-fiobank
Author: Martin Voldrich
Author-email: rbas.cz@gmail.com
License: Copyright (c) 2013, Martin Voldrich <rbas.cz@gmail.com>
